ekr/__init__.py
ekr/core.py
ekr/example/__init__.py
ekr/example/example.py
ekr/example/plugins/__init__.py
ekr/example/plugins/hello/__init__.py
ekr/example/plugins/hello/hello_core.py
ekr-0.1.4.2.dist-info/METADATA
ekr-0.1.4.2.dist-info/WHEEL
ekr-0.1.4.2.dist-info/top_level.txt
ekr-0.1.4.2.dist-info/RECORD
