Metadata-Version: 2.1
Name: ekr
Version: 0.1.4.2
Summary: MicroKernel based on eventframework as it's inner core. Use python project as plugin.
Home-page: UNKNOWN
Author: Eagle'sBaby
Author-email: 2229066748@qq.com
Maintainer: Eagle'sBaby
Maintainer-email: 2229066748@qq.com
License: Apache Licence 2.0
Keywords: microkernel,event-driven
Platform: all
Classifier: Programming Language :: Python
Classifier: Programming Language :: Python :: 3
Requires-Python: >=3
Requires-Dist: mkr (>=0.1.0)
Requires-Dist: efr (>=0.1.9)
